setup.py
devdoo/__init__.py
devdoo/actions.py
devdoo/check.py
devdoo/config.py
devdoo/console.py
devdoo/convert.py
devdoo/core.py
devdoo/database.py
devdoo/datafilter.py
devdoo/datarest.py
devdoo/datarest_db.py
devdoo/devdoo_brokers.py
devdoo/devdoo_databases.py
devdoo/devdoo_services.py
devdoo/endpoint.py
devdoo/package.py
devdoo/service.py
devdoo/service_db.py
devdoo/status.py
devdoo/validate.py
devdoo/xxxx.py
devdoo/i18n/__init__.py
devdoo/i18n/config.py
devdoo/i18n/resource_loader.py
devdoo/i18n/translations.py
devdoo/i18n/translator.py
devdoo/yaml/__init__.py
devdoo/yaml/composer.py
devdoo/yaml/constructor.py
devdoo/yaml/cyaml.py
devdoo/yaml/dumper.py
devdoo/yaml/emitter.py
devdoo/yaml/error.py
devdoo/yaml/events.py
devdoo/yaml/loader.py
devdoo/yaml/nodes.py
devdoo/yaml/parser.py
devdoo/yaml/reader.py
devdoo/yaml/representer.py
devdoo/yaml/resolver.py
devdoo/yaml/scanner.py
devdoo/yaml/serializer.py
devdoo/yaml/tokens.py
devdoo/i18n/__init__.py
devdoo/i18n/config.py
devdoo/i18n/resource_loader.py
devdoo/i18n/translations.py
devdoo/i18n/translator.py
devdoo/yaml/__init__.py
devdoo/yaml/composer.py
devdoo/yaml/constructor.py
devdoo/yaml/cyaml.py
devdoo/yaml/dumper.py
devdoo/yaml/emitter.py
devdoo/yaml/error.py
devdoo/yaml/events.py
devdoo/yaml/loader.py
devdoo/yaml/nodes.py
devdoo/yaml/parser.py
devdoo/yaml/reader.py
devdoo/yaml/representer.py
devdoo/yaml/resolver.py
devdoo/yaml/scanner.py
devdoo/yaml/serializer.py
devdoo/yaml/tokens.py
packagetest90.egg-info/PKG-INFO
packagetest90.egg-info/SOURCES.txt
packagetest90.egg-info/dependency_links.txt
packagetest90.egg-info/not-zip-safe
packagetest90.egg-info/top_level.txt